override_storage/__init__.py
override_storage/__version__.py
override_storage/compat.py
override_storage/runner.py
override_storage/storage.py
override_storage/utils.py
django_override_storage-0.3.2.dist-info/LICENSE
django_override_storage-0.3.2.dist-info/METADATA
django_override_storage-0.3.2.dist-info/WHEEL
django_override_storage-0.3.2.dist-info/top_level.txt
django_override_storage-0.3.2.dist-info/RECORD
